MANIFEST.in
README.rst
setup.cfg
setup.py
XStatic_Patternfly.egg-info/PKG-INFO
XStatic_Patternfly.egg-info/SOURCES.txt
XStatic_Patternfly.egg-info/dependency_links.txt
XStatic_Patternfly.egg-info/namespace_packages.txt
XStatic_Patternfly.egg-info/not-zip-safe
XStatic_Patternfly.egg-info/top_level.txt
xstatic/__init__.py
xstatic/pkg/__init__.py
xstatic/pkg/patternfly/__init__.py
xstatic/pkg/patternfly/data/css/patternfly-additions.css
xstatic/pkg/patternfly/data/css/patternfly-additions.css.map
xstatic/pkg/patternfly/data/css/patternfly-additions.min.css
xstatic/pkg/patternfly/data/css/patternfly-additions.min.css.map
xstatic/pkg/patternfly/data/css/patternfly.css
xstatic/pkg/patternfly/data/css/patternfly.css.map
xstatic/pkg/patternfly/data/css/patternfly.min.css
xstatic/pkg/patternfly/data/css/patternfly.min.css.map
xstatic/pkg/patternfly/data/fonts/FontAwesome.otf
xstatic/pkg/patternfly/data/fonts/OpenSans-Bold-webfont.eot
xstatic/pkg/patternfly/data/fonts/OpenSans-Bold-webfont.svg
xstatic/pkg/patternfly/data/fonts/OpenSans-Bold-webfont.ttf
xstatic/pkg/patternfly/data/fonts/OpenSans-Bold-webfont.woff
xstatic/pkg/patternfly/data/fonts/OpenSans-Bold-webfont.woff2
xstatic/pkg/patternfly/data/fonts/OpenSans-BoldItalic-webfont.eot
xstatic/pkg/patternfly/data/fonts/OpenSans-BoldItalic-webfont.svg
xstatic/pkg/patternfly/data/fonts/OpenSans-BoldItalic-webfont.ttf
xstatic/pkg/patternfly/data/fonts/OpenSans-BoldItalic-webfont.woff
xstatic/pkg/patternfly/data/fonts/OpenSans-BoldItalic-webfont.woff2
xstatic/pkg/patternfly/data/fonts/OpenSans-ExtraBold-webfont.eot
xstatic/pkg/patternfly/data/fonts/OpenSans-ExtraBold-webfont.svg
xstatic/pkg/patternfly/data/fonts/OpenSans-ExtraBold-webfont.ttf
xstatic/pkg/patternfly/data/fonts/OpenSans-ExtraBold-webfont.woff
xstatic/pkg/patternfly/data/fonts/OpenSans-ExtraBold-webfont.woff2
xstatic/pkg/patternfly/data/fonts/OpenSans-ExtraBoldItalic-webfont.eot
xstatic/pkg/patternfly/data/fonts/OpenSans-ExtraBoldItalic-webfont.svg
xstatic/pkg/patternfly/data/fonts/OpenSans-ExtraBoldItalic-webfont.ttf
xstatic/pkg/patternfly/data/fonts/OpenSans-ExtraBoldItalic-webfont.woff
xstatic/pkg/patternfly/data/fonts/OpenSans-ExtraBoldItalic-webfont.woff2
