Metadata-Version: 1.0
Name: XStatic-Patternfly
Version: 3.21.0.1
Summary: Patternfly 3.21.0 (XStatic packaging standard)
Home-page: https://www.patternfly.org/
Author: David Moreau Simard
Author-email: dmsimard@redhat.com
License: Apache v2
Keywords: patternfly xstatic
Platform: any
